zalando_deploy_cli/__init__.py
zalando_deploy_cli/__main__.py
zalando_deploy_cli/api.py
zalando_deploy_cli/cli.py
zalando_deploy_cli/templates/senza/NOTES.txt
zalando_deploy_cli/templates/senza/deployment.yaml
zalando_deploy_cli/templates/senza/pipeline.yaml
zalando_deploy_cli/templates/senza/apply/credentials.yaml
zalando_deploy_cli/templates/senza/apply/ingress.yaml
zalando_deploy_cli/templates/senza/apply/service.yaml
zalando_deploy_cli/templates/webapp/NOTES.txt
zalando_deploy_cli/templates/webapp/deployment.yaml
zalando_deploy_cli/templates/webapp/pipeline.yaml
zalando_deploy_cli/templates/webapp/apply/ingress.yaml
zalando_deploy_cli/templates/webapp/apply/service.yaml
zalando_deploy_cli/templates/webapp_appdynamics/NOTES.txt
zalando_deploy_cli/templates/webapp_appdynamics/deployment.yaml
zalando_deploy_cli/templates/webapp_appdynamics/pipeline.yaml
zalando_deploy_cli/templates/webapp_appdynamics/apply/ingress.yaml
zalando_deploy_cli/templates/webapp_appdynamics/apply/service.yaml
zalando_deploy_cli-1.0.10.dist-info/DESCRIPTION.rst
zalando_deploy_cli-1.0.10.dist-info/METADATA
zalando_deploy_cli-1.0.10.dist-info/RECORD
zalando_deploy_cli-1.0.10.dist-info/WHEEL
zalando_deploy_cli-1.0.10.dist-info/entry_points.txt
zalando_deploy_cli-1.0.10.dist-info/metadata.json
zalando_deploy_cli-1.0.10.dist-info/top_level.txt
