Metadata-Version: 2.0
Name: zalando-deploy-cli
Version: 1.0.10
Summary: UNKNOWN
Home-page: https://github.com/zalando-incubator/zalando-deploy-cli
Author: Zalando SE
Author-email: UNKNOWN
License: MIT
Platform: UNKNOWN
Classifier: Programming Language :: Python
Classifier: Programming Language :: Python :: 3.4
Classifier: Programming Language :: Python :: 3.5
Classifier: Development Status :: 5 - Production/Stable
Classifier: Intended Audience :: Developers
Classifier: Operating System :: OS Independent
Requires-Dist: boto3
Requires-Dist: clickclick
Requires-Dist: pystache
Requires-Dist: requests
Requires-Dist: stups-pierone
Requires-Dist: stups-zign
Requires-Dist: zalando-aws-cli (>=1.1.8)
Requires-Dist: zalando-kubectl (>=0.8)
